package_lab2
