Metadata-Version: 1.0
Name: package-lab2
Version: 0.3
Summary: Package for Lab 2...
Home-page: http://example.com
Author: me me me
Author-email: wooooah@gmail.com
License: UNKNOWN
Platform: UNKNOWN
